_foo.cpython-311-x86_64-linux-gnu.so
tensorflow_recommenders_addons_gpu-0.7.2.dist-info/RECORD
tensorflow_recommenders_addons_gpu-0.7.2.dist-info/METADATA
tensorflow_recommenders_addons_gpu-0.7.2.dist-info/WHEEL
tensorflow_recommenders_addons_gpu-0.7.2.dist-info/top_level.txt
tensorflow_recommenders_addons_gpu-0.7.2.dist-info/LICENSE
tensorflow_recommenders_addons/register.py
tensorflow_recommenders_addons/conftest.py
tensorflow_recommenders_addons/__init__.py
tensorflow_recommenders_addons/version.py
tensorflow_recommenders_addons/utils/ensure_tf_install.py
tensorflow_recommenders_addons/utils/test_utils.py
tensorflow_recommenders_addons/utils/check_platform.py
tensorflow_recommenders_addons/utils/__init__.py
tensorflow_recommenders_addons/utils/types.py
tensorflow_recommenders_addons/utils/resource_loader.py
tensorflow_recommenders_addons/dynamic_embedding/__init__.py
tensorflow_recommenders_addons/dynamic_embedding/core/_cuckoo_hashtable_ops.so
tensorflow_recommenders_addons/dynamic_embedding/core/_redis_table_ops.so
tensorflow_recommenders_addons/dynamic_embedding/core/_hkv_ops.so
tensorflow_recommenders_addons/dynamic_embedding/core/_data_flow_ops.so
tensorflow_recommenders_addons/dynamic_embedding/core/_math_ops.so
tensorflow_recommenders_addons/dynamic_embedding/python/__init__.py
tensorflow_recommenders_addons/dynamic_embedding/python/ops/shadow_embedding_ops.py
tensorflow_recommenders_addons/dynamic_embedding/python/ops/distributed_embedding_variable.py
tensorflow_recommenders_addons/dynamic_embedding/python/ops/dynamic_embedding_variable.py
tensorflow_recommenders_addons/dynamic_embedding/python/ops/math_ops.py
tensorflow_recommenders_addons/dynamic_embedding/python/ops/redis_table_ops.py
tensorflow_recommenders_addons/dynamic_embedding/python/ops/ragged_embedding_ops.py
tensorflow_recommenders_addons/dynamic_embedding/python/ops/data_flow_grad.py
tensorflow_recommenders_addons/dynamic_embedding/python/ops/dynamic_embedding_creator.py
tensorflow_recommenders_addons/dynamic_embedding/python/ops/__init__.py
tensorflow_recommenders_addons/dynamic_embedding/python/ops/cuckoo_hashtable_ops.py
tensorflow_recommenders_addons/dynamic_embedding/python/ops/dynamic_embedding_optimizer.py
